whatdidyoudo/__init__.py
whatdidyoudo/app.py
whatdidyoudo/static/favicon.svg
whatdidyoudo/static/style.css
whatdidyoudo/templates/index.html
whatdidyoudo/templates/result.html
whatdidyoudo/templates/static_page.html
whatdidyoudo-1.2.0.dist-info/METADATA
whatdidyoudo-1.2.0.dist-info/WHEEL
whatdidyoudo-1.2.0.dist-info/RECORD
