Metadata-Version: 2.4
Name: whatdidyoudo
Version: 1.2.0
Summary: A minimal Flask app that shows the amount of OpenStreetMap changes made by a user on a day.
Project-URL: Homepage, https://github.com/rompe/whatdidyoudo
Project-URL: Issues, https://github.com/rompe/whatdidyoudo/issues
Author-email: Ulf Rompe <whatdidyoudo.rompe.org@rompe.org>
License: MIT
Requires-Python: >=3.11
Requires-Dist: flask-caching==2.3.1
Requires-Dist: flask-limiter>=4.0.0
Requires-Dist: flask>=3.0.3
Requires-Dist: requests>=2.32.4
Provides-Extra: dev
Requires-Dist: hatchling>=1.27.0; extra == 'dev'
Requires-Dist: pytest>=9.0.0; extra == 'dev'
Requires-Dist: ruff>=0.13.2; extra == 'dev'
Requires-Dist: twine>=6.2.0; extra == 'dev'
Requires-Dist: types-requests>=2.32.4; extra == 'dev'
